pulsar_django-0.2.0.dist-info/DESCRIPTION.rst
pulsar_django-0.2.0.dist-info/METADATA
pulsar_django-0.2.0.dist-info/RECORD
pulsar_django-0.2.0.dist-info/WHEEL
pulsar_django-0.2.0.dist-info/metadata.json
pulsar_django-0.2.0.dist-info/top_level.txt
pulse/__init__.py
pulse/wsgi.py
pulse/management/__init__.py
pulse/management/commands/__init__.py
pulse/management/commands/pulse.py
